Workbook

Sheet Overview
A1: Notable Finance — Desktop App Progress
A2: Offline-first Electron desktop client. Local SQLite is the source of truth; Notion is a bidirectional mirror. Phases 0-1 complete and verified on 2026-07-21: the app is a fully usable offline daily driver (local CRUD, real-time derived balances, 9 sections, multi-window). Next: Phase 2 (Notion onboarding + push).
A4: Overall Progress
A5: Total items | B5: =COUNTA('Development Plan'!$B$5:$B$100) | C5: Done | D5: =COUNTIF('Development Plan'!$E$5:$E$100,"Done") | E5: % Complete | F5: =IFERROR(D5/B5,0)
A7: Progress by Phase
A8: Phase | B8: Total | C8: Not Started | D8: In Progress | E8: Done | F8: Blocked
A9: Phase 0 — Scaffold & shared logic | B9: =COUNTIF('Development Plan'!$A$5:$A$100,"Phase 0") | C9: =COUNTIFS('Development Plan'!$A$5:$A$100,"Phase 0",'Development Plan'!$E$5:$E$100,"Not Started") | D9: =COUNTIFS('Development Plan'!$A$5:$A$100,"Phase 0",'Development Plan'!$E$5:$E$100,"In Progress") | E9: =COUNTIFS('Development Plan'!$A$5:$A$100,"Phase 0",'Development Plan'!$E$5:$E$100,"Done") | F9: =COUNTIFS('Development Plan'!$A$5:$A$100,"Phase 0",'Development Plan'!$E$5:$E$100,"Blocked")
A10: Phase 1 — Offline app (fully usable, no sync) | B10: =COUNTIF('Development Plan'!$A$5:$A$100,"Phase 1") | C10: =COUNTIFS('Development Plan'!$A$5:$A$100,"Phase 1",'Development Plan'!$E$5:$E$100,"Not Started") | D10: =COUNTIFS('Development Plan'!$A$5:$A$100,"Phase 1",'Development Plan'!$E$5:$E$100,"In Progress") | E10: =COUNTIFS('Development Plan'!$A$5:$A$100,"Phase 1",'Development Plan'!$E$5:$E$100,"Done") | F10: =COUNTIFS('Development Plan'!$A$5:$A$100,"Phase 1",'Development Plan'!$E$5:$E$100,"Blocked")
A11: Phase 2 — Onboarding + Push | B11: =COUNTIF('Development Plan'!$A$5:$A$100,"Phase 2") | C11: =COUNTIFS('Development Plan'!$A$5:$A$100,"Phase 2",'Development Plan'!$E$5:$E$100,"Not Started") | D11: =COUNTIFS('Development Plan'!$A$5:$A$100,"Phase 2",'Development Plan'!$E$5:$E$100,"In Progress") | E11: =COUNTIFS('Development Plan'!$A$5:$A$100,"Phase 2",'Development Plan'!$E$5:$E$100,"Done") | F11: =COUNTIFS('Development Plan'!$A$5:$A$100,"Phase 2",'Development Plan'!$E$5:$E$100,"Blocked")
A12: Phase 3 — Pull | B12: =COUNTIF('Development Plan'!$A$5:$A$100,"Phase 3") | C12: =COUNTIFS('Development Plan'!$A$5:$A$100,"Phase 3",'Development Plan'!$E$5:$E$100,"Not Started") | D12: =COUNTIFS('Development Plan'!$A$5:$A$100,"Phase 3",'Development Plan'!$E$5:$E$100,"In Progress") | E12: =COUNTIFS('Development Plan'!$A$5:$A$100,"Phase 3",'Development Plan'!$E$5:$E$100,"Done") | F12: =COUNTIFS('Development Plan'!$A$5:$A$100,"Phase 3",'Development Plan'!$E$5:$E$100,"Blocked")
A13: Phase 4 — Reconcile + Conflict | B13: =COUNTIF('Development Plan'!$A$5:$A$100,"Phase 4") | C13: =COUNTIFS('Development Plan'!$A$5:$A$100,"Phase 4",'Development Plan'!$E$5:$E$100,"Not Started") | D13: =COUNTIFS('Development Plan'!$A$5:$A$100,"Phase 4",'Development Plan'!$E$5:$E$100,"In Progress") | E13: =COUNTIFS('Development Plan'!$A$5:$A$100,"Phase 4",'Development Plan'!$E$5:$E$100,"Done") | F13: =COUNTIFS('Development Plan'!$A$5:$A$100,"Phase 4",'Development Plan'!$E$5:$E$100,"Blocked")
A14: Phase 5 — Package | B14: =COUNTIF('Development Plan'!$A$5:$A$100,"Phase 5") | C14: =COUNTIFS('Development Plan'!$A$5:$A$100,"Phase 5",'Development Plan'!$E$5:$E$100,"Not Started") | D14: =COUNTIFS('Development Plan'!$A$5:$A$100,"Phase 5",'Development Plan'!$E$5:$E$100,"In Progress") | E14: =COUNTIFS('Development Plan'!$A$5:$A$100,"Phase 5",'Development Plan'!$E$5:$E$100,"Done") | F14: =COUNTIFS('Development Plan'!$A$5:$A$100,"Phase 5",'Development Plan'!$E$5:$E$100,"Blocked")
A15: Total | B15: =SUM(B9:B14) | C15: =SUM(C9:C14) | D15: =SUM(D9:D14) | E15: =SUM(E9:E14) | F15: =SUM(F9:F14)
A17: Milestones
A18: Milestone | B18: Scope | C18: Items | D18: Done | E18: % Complete | F18: Reaching it means
A19: M1 — Offline app | B19: Phase 0, Phase 1 | C19: =COUNTIF('Development Plan'!$A$5:$A$100,"Phase 0")+COUNTIF('Development Plan'!$A$5:$A$100,"Phase 1") | D19: =COUNTIFS('Development Plan'!$A$5:$A$100,"Phase 0",'Development Plan'!$E$5:$E$100,"Done")+COUNTIFS('Development Plan'!$A$5:$A$100,"Phase 1",'Development Plan'!$E$5:$E$100,"Done") | E19: =IFERROR(D19/C19,0) | F19: Usable offline; real-time balances.
A20: M2 — Backup sync | B20: Phase 2, Phase 3 | C20: =COUNTIF('Development Plan'!$A$5:$A$100,"Phase 2")+COUNTIF('Development Plan'!$A$5:$A$100,"Phase 3") | D20: =COUNTIFS('Development Plan'!$A$5:$A$100,"Phase 2",'Development Plan'!$E$5:$E$100,"Done")+COUNTIFS('Development Plan'!$A$5:$A$100,"Phase 3",'Development Plan'!$E$5:$E$100,"Done") | E20: =IFERROR(D20/C20,0) | F20: Push + pull working (one-directional feel).
A21: M3 — Full sync | B21: Phase 4 | C21: =COUNTIF('Development Plan'!$A$5:$A$100,"Phase 4") | D21: =COUNTIFS('Development Plan'!$A$5:$A$100,"Phase 4",'Development Plan'!$E$5:$E$100,"Done") | E21: =IFERROR(D21/C21,0) | F21: Bidirectional reconcile + conflict resolver.
A22: M4 — Shippable | B22: Phase 5 | C22: =COUNTIF('Development Plan'!$A$5:$A$100,"Phase 5") | D22: =COUNTIFS('Development Plan'!$A$5:$A$100,"Phase 5",'Development Plan'!$E$5:$E$100,"Done") | E22: =IFERROR(D22/C22,0) | F22: Packaged installers for mac/linux/windows.
A24: Status Legend
A25: Not Started | B25: Planned but not yet begun.
A26: In Progress | B26: Actively being worked; acceptance not yet met.
A27: Done | B27: Complete and verified against its acceptance criterion.
A28: Blocked | B28: Cannot proceed without a dependency, decision, or access.

Sheet Development Plan
A1: Notable Finance — Desktop Development Plan
A2: Work items from wiki/desktop/development-plan.md. Edit the Status (dropdown) and Notes columns to track progress. Updated 2026-07-21.
A4: Phase | B4: ID | C4: Work Item | D4: Acceptance Criteria | E4: Status | F4: Notes / Evidence
A5: Phase 0 | B5: 0.1 | C5: pnpm workspace; notable-finance-app with electron-vite (main/preload/renderer) | D5: App window boots with HMR | E5: Done | F5: Verified 2026-07-21: pnpm workspace + electron-vite scaffold; build & typecheck clean; Electron window boots with Vite HMR at localhost:5173.
A6: Phase 0 | B6: 0.2 | C6: better-sqlite3 + drizzle wired; migrations run on start | D6: Empty DB created in userData | E6: Done | F6: Verified 2026-07-21: better-sqlite3 (rebuilt for Electron ABI) + drizzle wired; migrations run on start; DB created at userData/notable-finance-app/notable-finance.sqlite with all 10 tables.
A7: Phase 0 | B7: 0.3 | C7: Copy domain/types/mapping/reporting from web into src/main/domain + src/shared | D7: Unit tests for derivations pass | E7: Done | F7: Verified 2026-07-21: DTO types + resource-utils + local derivations in src/shared + src/main/domain; 16 derivation unit tests pass (vitest). Notion property mapping deferred to Phase 2 (bundled with the Notion adapter).
A8: Phase 0 | B8: 0.4 | C8: contextBridge preload + IPC skeleton | D8: Renderer calls a no-op window.api channel | E8: Done | F8: Verified 2026-07-21: contextBridge preload + ipcMain.handle skeleton (app:ping, db:health) with the ApiResult envelope; renderer roundtrip returns pong + the live table list.
A9: Phase 1 | B9: 1.1 | C9: SQLite schema for all resources + sync columns | D9: Schema matches local-data-schema.md | E9: Done | F9: Verified 2026-07-21: schema completed with pasabuy columns (migration 0001); all tables + sync columns per local-data-schema.md.
A10: Phase 1 | B10: 1.2 | C10: Local CRUD for incomes/expenses/scheduler (instant write, dirty) | D10: Create/edit/soft-delete works offline | E10: Done | F10: Verified 2026-07-21: repositories with instant writes, sync_state=dirty, mutation_queue journal, soft-delete via title rewrite; validation in main; full IPC surface. Live-run harness exercised create/update/soft-delete.
A11: Phase 1 | B11: 1.3 | C11: Derived values (balances, budgets, net, monthly) computed from SQLite | D11: Numbers match golden tests; update on edit | E11: Done | F11: Verified 2026-07-21: live golden checks PASS (income 50,000 / expense 11,500 / margin 38,500 / cash flow 73,000; credit balance -8,000, available 42,000); recompute + derived:updated on every edit; 27 unit tests green.
A12: Phase 1 | B12: 1.4 | C12: Ported renderer pages (Dashboard, Accounts, Income, Expense, Monitoring, Transfer, CC Payment, Alkansya, Receivables) | D12: Sections render from local data | E12: Done | F12: Verified 2026-07-21: all 9 sections render from local SQLite over window.api with the web view semantics (fixed categories Transfer/CC Payment/Savings, receivables = no account, income excludes auxiliary). Re-expressed UI (not pixel-ported); full CRUD forms + scheduler panel.
A13: Phase 1 | B13: 1.5 | C13: Multi-window; changes reflect across windows | D13: Two windows stay consistent | E13: Done | F13: Verified 2026-07-21: New Window (menu Cmd/Ctrl+N + IPC); records:changed/derived:updated broadcast to all windows; live run showed 2 windows each receiving all 18 events and refetching.
A14: Phase 2 | B14: 2.1 | C14: Notion Connect: token via safeStorage; discover + map databases | D14: Token stored in keychain, never in renderer | E14: Not Started
A15: Phase 2 | B15: 2.2 | C15: Schema verification (drift report) | D15: Verify passes on the mapped workspace | E15: Not Started
A16: Phase 2 | B16: 2.3 | C16: Push: create/update/soft-delete to Notion (writable fields only) | D16: Dirty records reach Notion; ids stored; idempotent | E16: Not Started
A17: Phase 3 | B17: 3.1 | C17: Initial pull populates SQLite | D17: Local store matches Notion after onboarding | E17: Not Started
A18: Phase 3 | B18: 3.2 | C18: Incremental pull via Search since last_pull_cursor | D18: Only changed pages fetched; cursor persists | E18: Not Started
A19: Phase 3 | B19: 3.3 | C19: Reference cache (accounts/categories) refresh on pull | D19: Selectors reflect Notion | E19: Not Started
A20: Phase 4 | B20: 4.1 | C20: Three-way merge (base/local/remote); auto-merge disjoint fields | D20: Scenario matrix tests pass | E20: Not Started
A21: Phase 4 | B21: 4.2 | C21: Conflict detection + log + resolver UI (prompt) | D21: Same-field conflict prompts and resolves | E21: Not Started
A22: Phase 4 | B22: 4.3 | C22: Sync modes (manual + interval push/pull); status indicator; badges | D22: Status/badges per offline-and-state-model.md | E22: Not Started
A23: Phase 4 | B23: 4.4 | C23: Mutation queue durability + rate-limit backoff | D23: Crash/429 simulations pass | E23: Not Started
A24: Phase 5 | B24: 5.1 | C24: electron-builder for mac/linux/windows; native rebuild | D24: Installers produced; app runs unsigned | E24: Not Started
A25: Phase 5 | B25: 5.2 | C25: Playwright + Electron e2e for core flows | D25: E2E suite green | E25: Not Started
A26: Phase 5 | B26: 5.3 | C26: CHANGELOG + versioning | D26: v0.1.0 tagged | E26: Not Started
